viva_datacreator-0.0.7.dist-info/licenses/LICENSE
vivadatacreator/__init__.py
vivadatacreator/class_dict.csv
vivadatacreator/data_augmentation.py
vivadatacreator/download_checkpoints.py
vivadatacreator/eighth_step.py
vivadatacreator/fifth_step.py
vivadatacreator/first_step.py
vivadatacreator/fourth_step.py
vivadatacreator/guimain.py
vivadatacreator/install.py
vivadatacreator/runtime_utils.py
vivadatacreator/sam2_resources.py
vivadatacreator/second_step.py
vivadatacreator/seventh_step.py
vivadatacreator/sixth_step.py
vivadatacreator/third_step.py
vivadatacreator/tooldata.py
vivadatacreator/GUI/forest-dark.tcl
vivadatacreator/GUI/forest-dark/border-accent-hover.png
vivadatacreator/GUI/forest-dark/border-accent.png
vivadatacreator/GUI/forest-dark/border-basic.png
vivadatacreator/GUI/forest-dark/border-hover.png
vivadatacreator/GUI/forest-dark/border-invalid.png
vivadatacreator/GUI/forest-dark/card.png
vivadatacreator/GUI/forest-dark/check-accent.png
vivadatacreator/GUI/forest-dark/check-basic.png
vivadatacreator/GUI/forest-dark/check-hover.png
vivadatacreator/GUI/forest-dark/check-tri-accent.png
vivadatacreator/GUI/forest-dark/check-tri-basic.png
vivadatacreator/GUI/forest-dark/check-tri-hover.png
vivadatacreator/GUI/forest-dark/check-unsel-accent.png
vivadatacreator/GUI/forest-dark/check-unsel-basic.png
vivadatacreator/GUI/forest-dark/check-unsel-hover.png
vivadatacreator/GUI/forest-dark/check-unsel-pressed.png
vivadatacreator/GUI/forest-dark/combo-button-basic.png
vivadatacreator/GUI/forest-dark/combo-button-focus.png
vivadatacreator/GUI/forest-dark/combo-button-hover.png
vivadatacreator/GUI/forest-dark/down.png
vivadatacreator/GUI/forest-dark/empty.png
vivadatacreator/GUI/forest-dark/hor-accent.png
vivadatacreator/GUI/forest-dark/hor-basic.png
vivadatacreator/GUI/forest-dark/hor-hover.png
vivadatacreator/GUI/forest-dark/notebook.png
vivadatacreator/GUI/forest-dark/off-accent.png
vivadatacreator/GUI/forest-dark/off-basic.png
vivadatacreator/GUI/forest-dark/off-hover.png
vivadatacreator/GUI/forest-dark/on-accent.png
viva_datacreator-0.0.7.dist-info/METADATA
viva_datacreator-0.0.7.dist-info/WHEEL
viva_datacreator-0.0.7.dist-info/entry_points.txt
viva_datacreator-0.0.7.dist-info/top_level.txt
viva_datacreator-0.0.7.dist-info/RECORD
