Metadata-Version: 2.4
Name: viva-datacreator
Version: 0.0.7
Summary: An open-source tool for creating image segmentation datasets from videos using SAM 2
Author-email: "Miguel S. Soriano-García, Diego Mercado-Ravell, Israel Becerra, Julio De La Torre-Vanegas" <m16soriano@gmail.com>
License: MIT
Classifier: Development Status :: 3 - Alpha
Classifier: Intended Audience :: Developers
Classifier: Intended Audience :: Science/Research
Classifier: Programming Language :: Python :: 3
Classifier: Programming Language :: Python :: 3.12
Classifier: Operating System :: OS Independent
Classifier: Topic :: Scientific/Engineering :: Artificial Intelligence
Classifier: Topic :: Software Development :: Libraries :: Python Modules
Requires-Python: >=3.12
License-File: LICENSE
Requires-Dist: pyyaml>=6.0.3
Requires-Dist: torch>=2.7.0
Requires-Dist: torchvision>=0.22.0
Requires-Dist: sam2
Requires-Dist: markupsafe<3.0
Requires-Dist: opencv-python>=4.11.0.86
Requires-Dist: matplotlib>=3.10.7
Requires-Dist: sahi>=0.11.36
Requires-Dist: pandas>=2.3.3
Requires-Dist: ipython>=9.7.0
Requires-Dist: ultralytics>=8.3.228
Requires-Dist: tqdm>=4.67.1
Requires-Dist: deep-sort-realtime>=1.3.2
Requires-Dist: setuptools<71
Requires-Dist: typer>=0.20.0
Provides-Extra: docs
Requires-Dist: mkdocs>=1.6.1; extra == "docs"
Requires-Dist: mkdocs-material>=9.6.17; extra == "docs"
Requires-Dist: mkdocstrings[python]>=0.26.1; extra == "docs"
Dynamic: license-file
